numersys/__init__.py
numersys/exceptions.py
numersys/math.py
numersys-0.0.3.dist-info/METADATA
numersys-0.0.3.dist-info/WHEEL
numersys-0.0.3.dist-info/licenses/LICENSE
numersys-0.0.3.dist-info/RECORD
