Metadata-Version: 2.4
Name: numersys
Version: 0.0.3
Summary: Library for converting numbers between various numeral systems.
Project-URL: Homepage, https://github.com/treizd/NumSystems/tree/master
Project-URL: Issues, https://github.com/treizd/NumSystems/issues
Author-email: treizd <sqeshexaero@gmail.com>
License-File: LICENSE
Classifier: License :: OSI Approved :: MIT License
Classifier: Operating System :: OS Independent
Classifier: Programming Language :: Python :: 3
Requires-Python: >=3.6.0
